cryt/__init__.py
cryt/client.py
cryt/command/__init__.py
cryt/command/cancel.py
cryt/command/get.py
cryt/command/order.py
cryt/main.py
cryt-0.1.0.dist-info/entry_points.txt
cryt-0.1.0.dist-info/WHEEL
cryt-0.1.0.dist-info/METADATA
cryt-0.1.0.dist-info/RECORD
